LICENSE
MANIFEST.in
README.rst
setup.py
django_pragmatic.egg-info/PKG-INFO
django_pragmatic.egg-info/SOURCES.txt
django_pragmatic.egg-info/dependency_links.txt
django_pragmatic.egg-info/requires.txt
django_pragmatic.egg-info/top_level.txt
pragmatic/__init__.py
pragmatic/authentication.py
pragmatic/context_processors.py
pragmatic/decorators.py
pragmatic/fields.py
pragmatic/filters.py
pragmatic/forms.py
pragmatic/helpers.py
pragmatic/jobs.py
pragmatic/loghandlers.py
pragmatic/managers.py
pragmatic/middleware.py
pragmatic/mixins.py
pragmatic/panels.py
pragmatic/querysets.py
pragmatic/routers.py
pragmatic/select2.py
pragmatic/serializers.py
pragmatic/signals.py
pragmatic/utils.py
pragmatic/views.py
pragmatic/widgets.py
pragmatic/locale/sk/LC_MESSAGES/django.mo
pragmatic/locale/sk/LC_MESSAGES/django.po
pragmatic/management/__init__.py
pragmatic/management/commands/__init__.py
pragmatic/management/commands/clean_migrations.py
pragmatic/management/commands/rqscheduler.py
pragmatic/migrations/0001_initial.py
pragmatic/migrations/0002_auto_20201207_1214.py
pragmatic/migrations/0003_alter_deletedobject_options_and_more.py
pragmatic/migrations/__init__.py
pragmatic/models/__init__.py
pragmatic/models/expressions.py
pragmatic/models/functions.py
pragmatic/static/pragmatic/js/city-autocomplete.js
pragmatic/static/pragmatic/js/date-and-time-picker.js
pragmatic/static/pragmatic/js/forms.js
pragmatic/static/pragmatic/js/grouped-checkboxes.js
pragmatic/static/pragmatic/js/map-widget-utils.js
pragmatic/static/pragmatic/js/sliders.js
pragmatic/templates/maintenance_mode.html
pragmatic/templates/admin/chart.html
pragmatic/templates/helpers/breadcrumbs.html
pragmatic/templates/helpers/confirm_delete.html
pragmatic/templates/helpers/display_modes.html
pragmatic/templates/helpers/filter_values.html
pragmatic/templates/helpers/messages.html
pragmatic/templates/helpers/pagination-listview.html
pragmatic/templates/helpers/pagination.html
pragmatic/templates/helpers/sorting.html
pragmatic/templates/panels/sql_explain.html
pragmatic/templates/widgets/slider_input.html
pragmatic/templatetags/__init__.py
pragmatic/templatetags/pragmatic_tags.py