Metadata-Version: 2.1
Name: django-pragmatic
Version: 6.0.3
Summary: Pragmatic tools and utilities for Django projects
Home-page: https://github.com/PragmaticMates/django-pragmatic
Author: Pragmatic Mates
Author-email: info@pragmaticmates.com
Maintainer: Pragmatic Mates
Maintainer-email: info@pragmaticmates.com
License: BSD License
Keywords: django pragmatic tools utils
Classifier: Programming Language :: Python
Classifier: Programming Language :: Python :: 2.6
Classifier: Programming Language :: Python :: 2.7
Classifier: Operating System :: OS Independent
Classifier: Environment :: Web Environment
Classifier: Intended Audience :: Developers
Classifier: Framework :: Django
Classifier: License :: OSI Approved :: BSD License
Classifier: Development Status :: 3 - Alpha
License-File: LICENSE
Requires-Dist: django>=3.2
Requires-Dist: django-filter
Requires-Dist: python-pragmatic
